safari_cloud_tabs-0.1.1.dist-info/licenses/LICENSE
tabs/__init__.py
tabs/cli.py
safari_cloud_tabs-0.1.1.dist-info/METADATA
safari_cloud_tabs-0.1.1.dist-info/WHEEL
safari_cloud_tabs-0.1.1.dist-info/entry_points.txt
safari_cloud_tabs-0.1.1.dist-info/top_level.txt
safari_cloud_tabs-0.1.1.dist-info/RECORD
