Metadata-Version: 2.4
Name: safari-cloud-tabs
Version: 0.1.1
Summary: A command-line tool for managing Safari iCloud tabs
Author-email: Osvaldo Santana Neto <safari-cloud-tabs@osantana.me>
License-Expression: LicenseRef-Anti-Capitalist-1.4
Project-URL: Homepage, https://github.com/osantana/safari-cloud-tabs
Project-URL: Repository, https://github.com/osantana/safari-cloud-tabs
Keywords: safari,icloud,tabs,browser,macos
Classifier: Development Status :: 4 - Beta
Classifier: Environment :: Console
Classifier: Intended Audience :: Developers
Classifier: Intended Audience :: End Users/Desktop
Classifier: Operating System :: MacOS :: MacOS X
Classifier: Programming Language :: Python :: 3
Classifier: Programming Language :: Python :: 3.9
Classifier: Programming Language :: Python :: 3.10
Classifier: Programming Language :: Python :: 3.11
Classifier: Programming Language :: Python :: 3.12
Classifier: Programming Language :: Python :: 3.13
Classifier: Topic :: Utilities
Requires-Python: >=3.9
License-File: LICENSE
Dynamic: license-file
